{
    "objective":  "ENGREMIAT_FIRST_REAL_CONTROLLED_VALUE_FLOW",
    "stage":  "E97",
    "receipt_type":  "HUMAN_NEED_INTAKE_SETUP",
    "created_utc":  "2026-06-17T11:24:39.3997536Z",
    "created_files":  [
                          "data\\human-need-intake-097\\human-need-intake-model.json",
                          "data\\human-need-intake-097\\human-need-intake-record.json",
                          "data\\human-need-intake-097\\first-real-flow-inbox-entry.json"
                      ],
    "need_id":  "HN-097-001",
    "case_id":  "FRF-096-001",
    "need_executes":  false,
    "apply_executed":  false,
    "auto_apply":  false,
    "remote_execution":  false,
    "git_write":  false,
    "external_network":  false,
    "worker_executed":  false,
    "kanban_real_write":  false
}
