{
    "package_id":  "ENGREMIAT_OBSIDIAN_KANBAN_LAB_001",
    "stage":  "E01_CREATE_LAB_VAULT_AND_SEED_OBJECTS",
    "status":  "PASS",
    "vault":  "C:\\ENGREMIAT_CORE\\obsidian\\ENGREMIAT_OBSIDIAN_KANBAN_LAB",
    "needs":  3,
    "cards":  3,
    "manual_step":  "Open Obsidian vault and mark CARD-001 as GO",
    "git":  false,
    "network":  false,
    "browser":  false,
    "cline_write":  false,
    "worker_real_execution":  false,
    "next":  "MANUAL_OPEN_OBSIDIAN_LAB_AND_MARK_CARD_001_GO"
}
