{
    "objective_id":  "DEFINE_REAL_EXECUTION_LAUNCHER_REUSABLE_MVP_184_187",
    "stage":  "E187",
    "status":  "DONE",
    "readiness":  100,
    "launcher_exists":  true,
    "human_approval_exists":  true,
    "dashboard_created":  true,
    "manual_created":  true,
    "close_report_created":  true,
    "next_objective_created":  true,
    "created_at":  "2026-06-17T18:31:44.5901128+02:00",
    "outputs":  [
                    "C:\\ENGREMIAT_CORE\\dashboard\\launcher-dashboard\\index.html",
                    "C:\\ENGREMIAT_CORE\\data\\real-execution-launcher-187\\LAUNCHER_MANUAL.md",
                    "C:\\ENGREMIAT_CORE\\data\\real-execution-launcher-187\\launcher-close-report.md",
                    "C:\\ENGREMIAT_CORE\\data\\real-execution-launcher-187\\next-launcher-objective.md"
                ]
}
