{
    "id":  "MODULE_contrato_objetivo",
    "name":  "Contrato y objetivo",
    "type":  "REUSABLE_MODULE_TEMPLATE",
    "objective":  "Definir contrato minimo de modulo con objetivo, alcance, criterios de cierre y trazabilidad.",
    "objective_status":  "TEMPLATE_READY",
    "reusable":  true,
    "tags":  [
                 "contract",
                 "objective",
                 "scope"
             ],
    "created_at":  "2026-06-19T19:44:48",
    "source":  "E07A_SEED_REUSABLE_MODULE_LIBRARY",
    "vault":  "BOVEDA_MODULO",
    "lifecycle":  "ACTIVE_IN_PROJECT",
    "library_status":  "REUSED_IN_PROJECT",
    "project_path":  "C:\\Users\\pc\\Desktop\\ENGREMIAT_OPERATOR\\ENGREMIAT_PROJECT_p3_20260619-224903"
}
