{
    "package":  "ENGREMIAT_OPERATOR_V1_MEMORY_DOCS_SCREEN_001",
    "stage":  "E03_CREATE_MEMORY_DOCS_SCREEN_READONLY",
    "status":  "PASS",
    "created_at":  "2026-06-22T10:27:58",
    "screen":  "C:\\ENGREMIAT_CORE\\tools\\operator-v1\\operator-v1-memory-docs-screen.ps1",
    "parse":  true,
    "json_smoke":  true,
    "latest":  "C:\\ENGREMIAT_CORE\\data\\operator-v1-memory-docs-screen\\memory-docs-screen-view.latest.json",
    "index":  "C:\\ENGREMIAT_CORE\\documents\\operator-v1-memory-docs-screen\\MEMORY_DOCS_SCREEN_INDEX.md",
    "doc_dirs_count":  130,
    "doc_files_count":  360,
    "index_count":  12,
    "contract_count":  57,
    "evidence_count":  96,
    "state_count":  62,
    "manual_count":  102,
    "reports_recent_count":  10,
    "head":  "fd6e11f4",
    "rev_sync":  "0\t6",
    "tree_clean_before":  false,
    "push_executed":  false,
    "fetch_executed":  false,
    "merge_executed":  false,
    "delete_files":  false,
    "next":  "E04_GATE_LAUNCHER_INTEGRATION_MEMORY_DOCS"
}
