{
    "package":  "ENGREMIAT_OPERATOR_V1_HEALTH_LAUNCHERS_SCREEN_001",
    "stage":  "E03_CREATE_HEALTH_LAUNCHERS_SCREEN_READONLY",
    "status":  "PASS",
    "created_at":  "2026-06-22T10:48:45",
    "screen":  "C:\\ENGREMIAT_CORE\\tools\\operator-v1\\operator-v1-health-launchers-screen.ps1",
    "parse":  true,
    "json_smoke":  true,
    "latest":  "C:\\ENGREMIAT_CORE\\data\\operator-v1-health-launchers-screen\\health-launchers-screen-view.latest.json",
    "index":  "C:\\ENGREMIAT_CORE\\documents\\operator-v1-health-launchers-screen\\HEALTH_LAUNCHERS_SCREEN_INDEX.md",
    "health_dirs_count":  104,
    "health_files_count":  416,
    "launcher_count":  225,
    "health_count":  21,
    "smoke_count":  108,
    "repair_count":  43,
    "status_count":  19,
    "reports_recent_count":  10,
    "head":  "ca44ce5a",
    "rev_sync":  "0\t10",
    "tree_clean_before":  false,
    "push_executed":  false,
    "fetch_executed":  false,
    "merge_executed":  false,
    "delete_files":  false,
    "next":  "E04_GATE_LAUNCHER_INTEGRATION_HEALTH_LAUNCHERS"
}
