{
    "objective":  "ENGREMIAT_LOCAL_MULTIWORKER_LAUNCH_AND_LINK_009A_N1",
    "profile_id":  "LOCAL-MACHINE-PROFILE-N1",
    "computer_name":  "DESKTOP-RLPN1LL",
    "user_name":  "sacan",
    "cwd":  "C:\\Users\\sacan\\Desktop\\ENGREMIAT_CORE",
    "os":  "Microsoft Windows NT 10.0.19045.0",
    "powershell_version":  "5.1.19041.6456",
    "timestamp_utc":  "2026-06-16T12:38:35.9490628Z",
    "level":  "N1_LOCAL_PARTIAL_READINESS",
    "main_pc_required_for_local_prep":  false,
    "main_pc_required_for_full_test":  true,
    "remote_execution":  false,
    "ssh":  false,
    "git_write":  false
}
