{
    "objective_id":  "DEFINE_UNIFIED_ENTRYPOINT_PLAN_LAUNCHER_MVP_192_195",
    "stage":  "E192",
    "status":  "READY",
    "readiness":  100,
    "contract_created":  true,
    "policy_created":  true,
    "candidate_created":  true,
    "next":  "E193 Unified preview \u0026 UX readonly",
    "created_at":  "2026-06-17T18:54:45.7453987+02:00",
    "outputs":  [
                    "C:\\ENGREMIAT_CORE\\data\\unified-entrypoint-192\\unified-entrypoint-contract.json",
                    "C:\\ENGREMIAT_CORE\\data\\unified-entrypoint-192\\unified-entrypoint-policy.json",
                    "C:\\ENGREMIAT_CORE\\data\\unified-entrypoint-192\\unified-entry-candidate.json"
                ]
}
