{
    "schema":  "engremiat.system_observer_canonical_action_preview.v1",
    "package_id":  "ENGREMIAT_SYSTEM_OBSERVER_001",
    "stage":  "E08_SYSTEM_OBSERVER_PREPARE_TASK_TO_CANONICAL_ACTION_BRIDGE",
    "created_at":  "2026-06-20T15:30:22",
    "status":  "READY",
    "mode":  "DRY_RUN_PREVIEW_NO_MUTATION_NO_EXECUTION",
    "action_id":  "OBSERVER-CANONICAL-ACTION-OBS-TASK-014-growth",
    "source_task_id":  "OBS-TASK-014",
    "would_do":  [
                     "create canonical runtime action package",
                     "create human gate proposal",
                     "wait explicit authorization",
                     "execute only through canonical runtime after approval"
                 ],
    "would_not_do":  [
                         "modify project files now",
                         "execute worker",
                         "open browser",
                         "use network",
                         "run git",
                         "delete or move files"
                     ],
    "planned_state":  {
                          "gate_status_before":  "PENDING",
                          "gate_status_after":  "APPROVED_ONLY_IF_HUMAN_AUTHORIZES",
                          "execution_status_before":  "NOT_EXECUTED",
                          "execution_status_after":  "EXECUTED_ONLY_AFTER_RUNTIME_AUTH"
                      },
    "safety":  {
                   "real_execution":  false,
                   "system_mutation":  false,
                   "action_executed":  false,
                   "worker":  false,
                   "browser":  false,
                   "network":  false,
                   "git":  false
               },
    "next":  "E09_SYSTEM_OBSERVER_SMOKE_TASK_TO_ACTION_BRIDGE_NO_EXECUTION"
}
