{
    "objective":  "ENGREMIAT_CONTROLLED_REAL_WORKER_DAILY_VALUE_LOOP_056_065",
    "stage":  "E56",
    "receipt_id":  "E56_WORKER_REAL_INPUT_GATE_RECEIPT",
    "contract":  "data\\worker-real-056\\worker-real-input-contract.json",
    "gate":  "data\\worker-real-056\\worker-real-execution-gate.json",
    "prompt_packet":  "prompts\\outbox\\WORKER_REAL_PROMPT_PACKET.md",
    "worker_executed":  false,
    "worker_real_execution_authorized":  false,
    "apply_executed":  false,
    "auto_apply":  false,
    "remote_execution":  false,
    "git_write":  false,
    "external_network":  false,
    "created_at":  "2026-06-17T12:11:55"
}
